kaggler/__init__.py
kaggler/cli.py
kaggler/workflows.py
kaggler/automl/__init__.py
kaggler/automl/autosklearn_wrapper.py
kaggler/automl/base.py
kaggler/automl/benchmark.py
kaggler/automl/comparison.py
kaggler/automl/h2o_wrapper.py
kaggler/automl/hybrid.py
kaggler/automl/router.py
kaggler/automl/tpot_wrapper.py
kaggler/collaborative/__init__.py
kaggler/collaborative/celery_app.py
kaggler/collaborative/celeryconfig.py
kaggler/collaborative/coordinator.py
kaggler/collaborative/merge.py
kaggler/collaborative/protocol.py
kaggler/collaborative/sharing.py
kaggler/collaborative/tasks.py
kaggler/collaborative/tracking.py
kaggler/collaborative/worker.py
kaggler/core/__init__.py
kaggler/core/crossover.py
kaggler/core/evolution.py
kaggler/core/mutation.py
kaggler/core/pareto.py
kaggler/core/reflection.py
kaggler/dashboard/backend/__init__.py
kaggler/dashboard/backend/app.py
kaggler/dashboard/backend/config.py
kaggler/dashboard/backend/models.py
kaggler/dashboard/backend/routes.py
kaggler/dashboard/backend/websocket.py
kaggler/dashboard/backend/tests/__init__.py
kaggler/dashboard/backend/tests/test_api.py
kaggler/domains/__init__.py
kaggler/domains/finance/__init__.py
kaggler/domains/finance/analyzers.py
kaggler/domains/finance/metrics.py
kaggler/domains/finance/templates.py
kaggler/domains/finance/validators.py
kaggler/domains/legal/__init__.py
kaggler/domains/legal/extractor.py
kaggler/domains/legal/templates.py
kaggler/domains/manufacturing/__init__.py
kaggler/domains/manufacturing/inspector.py
kaggler/domains/manufacturing/spc.py
kaggler/domains/manufacturing/templates.py
kaggler/domains/medical/__init__.py
kaggler/domains/medical/extractors.py
kaggler/domains/medical/metrics.py
kaggler/domains/medical/templates.py
kaggler/domains/medical/validators.py
kaggler/kaggle/__init__.py
kaggler/kaggle/client.py
kaggler/kaggle/downloader.py
kaggler/kaggle/leaderboard.py
kaggler/kaggle/submitter.py
kaggler/marketplace/__init__.py
kaggler/marketplace/api.py
kaggler/marketplace/auth.py
kagglerboze-0.2.4.dist-info/licenses/LICENSE
kagglerboze-0.2.4.dist-info/METADATA
kagglerboze-0.2.4.dist-info/WHEEL
kagglerboze-0.2.4.dist-info/entry_points.txt
kagglerboze-0.2.4.dist-info/top_level.txt
kagglerboze-0.2.4.dist-info/RECORD
