Metadata-Version: 2.4
Name: kagglerboze
Version: 0.2.4
Summary: GEPA-powered ML automation for Kaggle - Achieve 90%+ accuracy in 30 minutes
Author-email: StarBoze <noreply@github.com>
License: MIT
Project-URL: Homepage, https://github.com/StarBoze/kagglerboze
Project-URL: Documentation, https://starboze.github.io/kagglerboze
Project-URL: Repository, https://github.com/StarBoze/kagglerboze
Project-URL: Bug Tracker, https://github.com/StarBoze/kagglerboze/issues
Keywords: kaggle,machine-learning,prompt-optimization,genetic-algorithm,llm,medical-nlp,financial-analysis,automl
Classifier: Development Status :: 4 - Beta
Classifier: Intended Audience :: Developers
Classifier: Intended Audience :: Science/Research
Classifier: License :: OSI Approved :: MIT License
Classifier: Programming Language :: Python :: 3
Classifier: Programming Language :: Python :: 3.8
Classifier: Programming Language :: Python :: 3.9
Classifier: Programming Language :: Python :: 3.10
Classifier: Programming Language :: Python :: 3.11
Classifier: Programming Language :: Python :: 3.12
Classifier: Topic :: Scientific/Engineering :: Artificial Intelligence
Classifier: Topic :: Software Development :: Libraries :: Python Modules
Requires-Python: >=3.8
License-File: LICENSE
Requires-Dist: numpy>=1.20.0
Requires-Dist: pandas>=1.3.0
Requires-Dist: anthropic>=0.18.0
Requires-Dist: kaggle>=1.5.16
Requires-Dist: tqdm>=4.65.0
Requires-Dist: pydantic>=2.0.0
Requires-Dist: python-dotenv>=1.0.0
Requires-Dist: rich>=13.0.0
Requires-Dist: click>=8.1.0
Provides-Extra: dev
Requires-Dist: pytest>=7.0.0; extra == "dev"
Requires-Dist: pytest-cov>=4.0.0; extra == "dev"
Requires-Dist: black>=23.0.0; extra == "dev"
Requires-Dist: flake8>=6.0.0; extra == "dev"
Requires-Dist: mypy>=1.0.0; extra == "dev"
Requires-Dist: isort>=5.12.0; extra == "dev"
Provides-Extra: finance
Requires-Dist: yfinance>=0.2.0; extra == "finance"
Requires-Dist: matplotlib>=3.5.0; extra == "finance"
Requires-Dist: seaborn>=0.12.0; extra == "finance"
Provides-Extra: medical
Requires-Dist: spacy>=3.5.0; extra == "medical"
Requires-Dist: scikit-learn>=1.2.0; extra == "medical"
Provides-Extra: tabular
Requires-Dist: xgboost>=1.7.0; extra == "tabular"
Requires-Dist: lightgbm>=3.3.0; extra == "tabular"
Requires-Dist: scikit-learn>=1.2.0; extra == "tabular"
Requires-Dist: scipy>=1.9.0; extra == "tabular"
Provides-Extra: automl
Requires-Dist: auto-sklearn>=0.15.0; extra == "automl"
Requires-Dist: TPOT>=0.12.0; extra == "automl"
Requires-Dist: h2o>=3.40.0; extra == "automl"
Requires-Dist: scikit-learn>=1.2.0; extra == "automl"
Requires-Dist: scipy>=1.9.0; extra == "automl"
Provides-Extra: collaborative
Requires-Dist: celery>=5.3.0; extra == "collaborative"
Requires-Dist: redis>=5.0.0; extra == "collaborative"
Requires-Dist: flower>=2.0.0; extra == "collaborative"
Requires-Dist: kombu>=5.3.0; extra == "collaborative"
Provides-Extra: all
Requires-Dist: kagglerboze[automl,collaborative,dev,finance,medical,tabular]; extra == "all"
Dynamic: license-file
